MANIFEST.in
README.rst
setup.py
pinmyreqs/__init__.py
pinmyreqs.egg-info/PKG-INFO
pinmyreqs.egg-info/SOURCES.txt
pinmyreqs.egg-info/dependency_links.txt
pinmyreqs.egg-info/entry_points.txt
pinmyreqs.egg-info/not-zip-safe
pinmyreqs.egg-info/top_level.txt