Metadata-Version: 1.1
Name: pinmyreqs
Version: 0.2
Summary: Pin your requirements.txt without adding new dependencies
Home-page: http://github.com/mdamien/pinmyreqs
Author: Damien MARIÉ
Author-email: damien@dam.io
License: MIT
Platform: UNKNOWN
Classifier: Intended Audience :: Developers
Classifier: Natural Language :: English
Classifier: License :: OSI Approved :: MIT License
Classifier: Programming Language :: Python :: 3
